cwl/__init__.py
cwl/cwl_eval.py
cwl/ruler/__init__.py
cwl/ruler/cwl_ruler.py
cwl/ruler/ranking.py
cwl/ruler/measures/__init__.py
cwl/ruler/measures/cwl_ap.py
cwl/ruler/measures/cwl_bpm.py
cwl/ruler/measures/cwl_dcg.py
cwl/ruler/measures/cwl_ift.py
cwl/ruler/measures/cwl_insq.py
cwl/ruler/measures/cwl_inst.py
cwl/ruler/measures/cwl_metrics.py
cwl/ruler/measures/cwl_npv.py
cwl/ruler/measures/cwl_precision.py
cwl/ruler/measures/cwl_rbp.py
cwl/ruler/measures/cwl_rr.py
cwl/ruler/measures/cwl_set.py
cwl/ruler/measures/cwl_tbg.py
cwl/ruler/measures/cwl_umeasure.py
cwl/seeker/__init__.py
cwl/seeker/common_helpers.py
cwl/seeker/topic_document_file_handler.py
cwl/seeker/trec_qrel_handler.py
cwl/seeker/trec_result_handler.py
cwl/tests/__init__.py
cwl/tests/common_metric_test.py
cwl/tests/ranking_test.py
cwl_eval-1.0.8.data/scripts/cwl-eval
cwl_eval-1.0.8.dist-info/LICENSE
cwl_eval-1.0.8.dist-info/METADATA
cwl_eval-1.0.8.dist-info/WHEEL
cwl_eval-1.0.8.dist-info/top_level.txt
cwl_eval-1.0.8.dist-info/RECORD
