Metadata-Version: 2.1
Name: cwl-eval
Version: 1.0.8
Summary: An information retrieval evaluation script based on the C/W/L framework that is TREC Compatible and provides a replacement for INST_EVAL, RBP_EVAL, TBG_EVAL, UMeasure and TREC_EVAL scripts. All measurements are reported in the same units making all metrics directly comparable.
Home-page: https://github.com/ireval/cwl
Author: Leif Azzopardi, Paul Thomas, Alistair Moffat
Author-email: leifos@acm.org, pathom@microsoft.com, ammoffat@unimelb.edu.au
License: UNKNOWN
Platform: UNKNOWN
Classifier: Intended Audience :: Science/Research
Classifier: Programming Language :: Python :: 3 :: Only
Classifier: Topic :: Scientific/Engineering :: Information Analysis
Classifier: License :: OSI Approved :: MIT License
Classifier: Development Status :: 3 - Alpha
Requires-Python: >=3
Requires-Dist: numpy
